secret_wichtel/__init__.py
secret_wichtel/secret_wichtel.py
secret_wichtel-0.1.1.dist-info/LICENSE
secret_wichtel-0.1.1.dist-info/WHEEL
secret_wichtel-0.1.1.dist-info/METADATA
secret_wichtel-0.1.1.dist-info/RECORD
